MANIFEST.in
README.txt
collecitve.shinythings-configure.zcml
setup.cfg
setup.py
collective/__init__.py
collective.shinythings.egg-info/PKG-INFO
collective.shinythings.egg-info/SOURCES.txt
collective.shinythings.egg-info/dependency_links.txt
collective.shinythings.egg-info/entry_points.txt
collective.shinythings.egg-info/namespace_packages.txt
collective.shinythings.egg-info/not-zip-safe
collective.shinythings.egg-info/requires.txt
collective.shinythings.egg-info/top_level.txt
collective/shinythings/__init__.py
collective/shinythings/configlet.py
collective/shinythings/configure.zcml
collective/shinythings/interfaces.py
collective/shinythings/profiles.zcml
collective/shinythings/setuphandlers.py
collective/shinythings/skins.zcml
collective/shinythings/tests.py
collective/shinythings/version.txt
collective/shinythings/fonts/Quicksand_Book-webfont.ttf
collective/shinythings/profiles/default/actionicons.xml
collective/shinythings/profiles/default/collective.shinythings_various.txt
collective/shinythings/profiles/default/controlpanel.xml
collective/shinythings/profiles/default/cssregistry.xml
collective/shinythings/profiles/default/import_steps.xml
collective/shinythings/profiles/default/jsregistry.xml
collective/shinythings/profiles/default/metadata.xml
collective/shinythings/profiles/default/propertiestool.xml
collective/shinythings/profiles/default/skins.xml
collective/shinythings/skins/shinythings/Blue Vinyl License.txt
collective/shinythings/skins/shinythings/Matchbook-cufon.js
collective/shinythings/skins/shinythings/Matchbook-webfont.eot
collective/shinythings/skins/shinythings/Matchbook-webfont.svg
collective/shinythings/skins/shinythings/Matchbook-webfont.ttf
collective/shinythings/skins/shinythings/Matchbook-webfont.woff
collective/shinythings/skins/shinythings/One by Four SIL Open Font License.txt
collective/shinythings/skins/shinythings/PT_Sans-cufon.js
collective/shinythings/skins/shinythings/PT_Sans-webfont.eot
collective/shinythings/skins/shinythings/PT_Sans-webfont.svg
collective/shinythings/skins/shinythings/PT_Sans-webfont.ttf
collective/shinythings/skins/shinythings/PT_Sans-webfont.woff
collective/shinythings/skins/shinythings/PT_Sans_Bold-cufon.js
collective/shinythings/skins/shinythings/PT_Sans_Bold-webfont.eot
collective/shinythings/skins/shinythings/PT_Sans_Bold-webfont.svg
