Metadata-Version: 1.0
Name: collective.shinythings
Version: 0.5dev-r117575
Summary: Jazz up your Plone theme
Home-page: http://medialog.no
Author: Espen Moe-Nilssen
Author-email: espen@medialog.no
License: GPL
Platform: UNKNOWN
Classifier: Programming Language :: Python
Classifier: Topic :: Software Development :: Libraries :: Python Modules
